discord/ext/pager/__init__.py
discord/ext/pager/py.typed
discord_ext_pager-1.1.3.dist-info/LICENSE
discord_ext_pager-1.1.3.dist-info/METADATA
discord_ext_pager-1.1.3.dist-info/WHEEL
discord_ext_pager-1.1.3.dist-info/top_level.txt
discord_ext_pager-1.1.3.dist-info/RECORD
