Metadata-Version: 2.1
Name: discord-ext-pager
Version: 1.1.3
Summary: A view-based paginator library for discord.py 2.0
Author: thegamecracks
Project-URL: Homepage, https://github.com/thegamecracks/discord-ext-pager
Keywords: discord,discord.py,paginator,view
Classifier: Development Status :: 5 - Production/Stable
Classifier: Framework :: AsyncIO
Classifier: Intended Audience :: Developers
Classifier: License :: OSI Approved
Classifier: License :: OSI Approved :: Mozilla Public License 2.0 (MPL 2.0)
Classifier: Programming Language :: Python
Classifier: Programming Language :: Python :: 3 :: Only
Classifier: Programming Language :: Python :: 3.8
Classifier: Programming Language :: Python :: 3.9
Classifier: Programming Language :: Python :: 3.10
Classifier: Programming Language :: Python :: 3.11
Classifier: Topic :: Software Development
Classifier: Topic :: Software Development :: Libraries
Classifier: Topic :: Software Development :: Libraries :: Python Modules
Classifier: Typing :: Typed
Requires-Python: >=3.8
License-File: LICENSE
Requires-Dist: discord.py >=2.0.0
Requires-Dist: typing-extensions >=4.5.0
